example_package/__init__.py
example_package/example.py
xqlpdemo-0.0.1.dist-info/LICENSE
xqlpdemo-0.0.1.dist-info/METADATA
xqlpdemo-0.0.1.dist-info/WHEEL
xqlpdemo-0.0.1.dist-info/top_level.txt
xqlpdemo-0.0.1.dist-info/RECORD
